setup.py
sfws/__init__.py
sfws/catalogs.py
sfws/client.py
sfws/orders.py
sfws/products.py
sfws/sfws.py
sfws.egg-info/PKG-INFO
sfws.egg-info/SOURCES.txt
sfws.egg-info/dependency_links.txt
sfws.egg-info/top_level.txt