Metadata-Version: 1.2
Name: sfws
Version: 2.0.3
Summary: SF Company
Home-page: http://odoo.com
Author: @rockscripts
Author-email: rockscripts@gmail.com
License: UNKNOWN
Platform: any
Classifier: License :: OSI Approved :: BSD License
Classifier: Programming Language :: Python :: 3
Classifier: Topic :: Software Development :: Libraries :: Python Modules
Requires-Python: >=2.7.*
